exporters/sql_export/__init__.py
exporters/sql_export/config.py
exporters/sql_export/gql_lora_cache_async.py
exporters/sql_export/lc_for_jobs_db.py
exporters/sql_export/lora_cache.py
exporters/sql_export/main.py
exporters/sql_export/sql_export.py
exporters/sql_export/sql_table_defs.py
exporters/sql_export/sql_url.py
exporters/sql_export/trigger.py
exporters/utils/priority_by_class.py
integrations/__init__.py
integrations/aarhus/config.py
integrations/aarhus/dar_helper.py
integrations/aarhus/initial.py
integrations/aarhus/initial_classes.py
integrations/aarhus/los_files.py
integrations/aarhus/los_import.py
integrations/aarhus/los_leder.py
integrations/aarhus/los_org.py
integrations/aarhus/los_pers.py
integrations/aarhus/los_stam.py
integrations/aarhus/payloads.py
integrations/aarhus/tests/__init__.py
integrations/aarhus/tests/conftest.py
integrations/aarhus/tests/helpers.py
integrations/aarhus/tests/strategies.py
integrations/aarhus/tests/test_config.py
integrations/aarhus/tests/test_initial.py
integrations/aarhus/tests/test_los_files.py
integrations/aarhus/tests/test_los_import.py
integrations/aarhus/tests/test_los_leder.py
integrations/aarhus/tests/test_los_org.py
integrations/aarhus/tests/test_los_pers.py
integrations/aarhus/tests/test_los_stam.py
integrations/aarhus/tests/test_payloads.py
integrations/aarhus/tests/test_util.py
integrations/aarhus/util.py
integrations/aarhus/uuids.py
integrations/ad_integration/__init__.py
integrations/ad_integration/ad_common.py
integrations/ad_integration/ad_exceptions.py
integrations/ad_integration/ad_fix_enddate.py
integrations/ad_integration/ad_jinja_filters.py
integrations/ad_integration/ad_life_cycle.py
integrations/ad_integration/ad_logger.py
integrations/ad_integration/ad_reader.py
integrations/ad_integration/ad_sync.py
integrations/ad_integration/ad_template_engine.py
integrations/ad_integration/ad_templates.py
integrations/ad_integration/ad_writer.py
integrations/ad_integration/import_ad_group_into_mo.py
dipex-5.62.0.dist-info/METADATA
dipex-5.62.0.dist-info/WHEEL
dipex-5.62.0.dist-info/RECORD
